witchtui/__init__.py
witchtui/errors.py
witchtui/layout.py
witchtui/layout_state.py
witchtui/state.py
witchtui/utils.py
witchtui/widgets.py
witchtui-0.1.3.dist-info/LICENSE.md
witchtui-0.1.3.dist-info/METADATA
witchtui-0.1.3.dist-info/WHEEL
witchtui-0.1.3.dist-info/entry_points.txt
witchtui-0.1.3.dist-info/RECORD
