Metadata-Version: 2.1
Name: witchtui
Version: 0.1.3
Summary: A Immediate Command line User Interface for Python
License: MIT
Author: François Poizat
Author-email: francois.poizat@gmail.com
Requires-Python: >=3.10,<4.0
Classifier: License :: OSI Approved :: MIT License
Classifier: Programming Language :: Python :: 3
Classifier: Programming Language :: Python :: 3.10
Classifier: Programming Language :: Python :: 3.11
